{"file": {"path": "/cs/home/cd271/Documents/Project/Examples/SemanticCodeSearch/Code2code/SearchEngine/content/keon/algorithms/algorithms/tree/bst/predecessor.py", "fileNameBase": "predecessor", "extension": "py"}, "functions": {"predecessor": {"args": ["root", "node"], "returns": ["pred"], "min_max_lineno": {"min_lineno": 1, "max_lineno": 10}, "source_code": "def predecessor(root, node):\n    pred = None\n    while root:\n        if node.val > root.val:\n            pred = root\n            root = root.right\n        else:\n            root = root.left\n    return pred"}}, "is_test": false}